fibonacci_generator_grossbeak/__init__.py
fibonacci_generator_grossbeak/main.py
fibonacci_generator_grossbeak-0.1.1.dist-info/METADATA
fibonacci_generator_grossbeak-0.1.1.dist-info/WHEEL
fibonacci_generator_grossbeak-0.1.1.dist-info/licenses/LICENSE
fibonacci_generator_grossbeak-0.1.1.dist-info/RECORD
